funciones.py
javmur-0.0.1.dist-info/METADATA
javmur-0.0.1.dist-info/WHEEL
javmur-0.0.1.dist-info/top_level.txt
javmur-0.0.1.dist-info/RECORD
